mpdfg/__init__.py
mpdfg/actions.py
mpdfg/dfg.py
mpdfg/dfg_builder.py
mpdfg/dfg_parameters.py
mpdfg/log_formatter.py
mpdfg/diagrammers/graphviz.py
mpdfg/diagrammers/mermaid.py
mpdfg/utils/actions.py
mpdfg/utils/builder.py
mpdfg/utils/color_scales.py
mpdfg/utils/constants.py
mpdfg/utils/diagrammer.py
mpdfg/utils/filters.py
mpdfg-0.0.5.dist-info/METADATA
mpdfg-0.0.5.dist-info/WHEEL
mpdfg-0.0.5.dist-info/licenses/LICENSE
mpdfg-0.0.5.dist-info/RECORD
