Metadata-Version: 2.3
Name: mpdfg
Version: 0.0.5
Summary: Package for multi perspective DFG visualization
Project-URL: Homepage, https://github.com/nicoabarca/mpdfg
Project-URL: Issues, https://github.com/nicoabarca/mpdfg/issues
Author-email: mpdfg <mpdfg.package@gmail.com>
License:                     GNU GENERAL PUBLIC LICENSE
Classifier: Intended Audience :: Developers
Classifier: Intended Audience :: Science/Research
Classifier: Operating System :: OS Independent
Classifier: Programming Language :: Python :: 3
Classifier: Topic :: Scientific/Engineering :: Visualization
Requires-Python: >=3.9
Requires-Dist: graphviz
Requires-Dist: matplotlib
Requires-Dist: numpy
Requires-Dist: pandas
Requires-Dist: pm4py
Requires-Dist: pyarrow
